README.md
setup.py
finbox/__init__.py
finbox.egg-info/PKG-INFO
finbox.egg-info/SOURCES.txt
finbox.egg-info/dependency_links.txt
finbox.egg-info/requires.txt
finbox.egg-info/top_level.txt
finbox/backtest/__init__.py
finbox/backtest/backtest.py
finbox/backtest/interesting_periods.py
finbox/backtest/plotting.py
finbox/backtest/pyfolio.py
finbox/backtest/report.py
finbox/backtest/plottings/__init__.py
finbox/backtest/plottings/_plot_echarts.py
finbox/backtest/plottings/_plot_matplotlib.py
finbox/backtest/plottings/_plot_meta.py
finbox/data/__init__.py
finbox/data/equity.py
finbox/data/options.py